README.rst
setup.cfg
setup.py
falkonryclient/__init__.py
falkonryclient.egg-info/PKG-INFO
falkonryclient.egg-info/SOURCES.txt
falkonryclient.egg-info/dependency_links.txt
falkonryclient.egg-info/not-zip-safe
falkonryclient.egg-info/requires.txt
falkonryclient.egg-info/top_level.txt
falkonryclient/helper/__init__.py
falkonryclient/helper/schema.py
falkonryclient/helper/utils.py
falkonryclient/helper/models/Assessment.py
falkonryclient/helper/models/AssessmentRequest.py
falkonryclient/helper/models/Datasource.py
falkonryclient/helper/models/Datastream.py
falkonryclient/helper/models/EntityMeta.py
falkonryclient/helper/models/Field.py
falkonryclient/helper/models/Input.py
falkonryclient/helper/models/Signal.py
falkonryclient/helper/models/Stats.py
falkonryclient/helper/models/Time.py
falkonryclient/helper/models/Tracker.py
falkonryclient/helper/models/__init__.py
falkonryclient/service/__init__.py
falkonryclient/service/entity.py
falkonryclient/service/falkonry.py
falkonryclient/service/http.py