Metadata-Version: 1.1
Name: falkonryclient
Version: 1.1.0
Summary: Falkonry Python Client to access Condition Prediction APIs
Home-page: https://github.com/Falkonry/falkonry-python-client
Author: Falkonry Inc
Author-email: info@falkonry.com
License: MIT
Download-URL: https://github.com/Falkonry/falkonry-python-client/tarball/1.1.0
Keywords: falkonry falkonryclient conditionprediction
Platform: UNKNOWN
